reformpy/Buck_api4ase.py
reformpy/Ewald.py
reformpy/M3GNet_api4ase.py
reformpy/SF_LJ_api4ase.py
reformpy/ThreeBodyTB_api4ase.py
reformpy/__init__.py
reformpy/calculator.py
reformpy/gulp_api4ase.py
reformpy/libfppy.py
reformpy/mixing.py
reformpy/xx.py
reformpy-1.3.1.dist-info/licenses/LICENSE.md
reformpy-1.3.1.dist-info/METADATA
reformpy-1.3.1.dist-info/WHEEL
reformpy-1.3.1.dist-info/top_level.txt
reformpy-1.3.1.dist-info/RECORD
