Metadata-Version: 2.4
Name: reformpy
Version: 1.3.1
Summary: Rational Exploration of Fingerprint-Oriented Relaxation Methodology
Home-page: https://github.com/Rutgers-ZRG/ReformPy
Author: Zhu Research Group
Author-email: li.zhu@rutgers.edu
Classifier: Programming Language :: Python :: 3
Classifier: License :: OSI Approved :: MIT License
Classifier: Operating System :: OS Independent
Requires-Python: >=3.8
License-File: LICENSE.md
Requires-Dist: numpy>=1.24.4
Requires-Dist: scipy>=1.10.1
Requires-Dist: numba>=0.58.1
Requires-Dist: ase>=3.22.1
Requires-Dist: libfp>=3.1.2
Requires-Dist: mpi4py<4.0,>=3.1.0
Dynamic: author
Dynamic: author-email
Dynamic: classifier
Dynamic: description
Dynamic: description-content-type
Dynamic: home-page
Dynamic: license-file
Dynamic: requires-dist
Dynamic: requires-python
Dynamic: summary
